Metadata-Version: 1.1
Name: cgns-wrapper
Version: 0.5.2
Summary: Using CGNS in Python
Home-page: https://github.com/chiao45/cgns_wrapper
Author: Qiao Chen
Author-email: benechiao@gmail.com
License: MIT
Keywords: Math
Platform: UNKNOWN
Classifier: Programming Language :: Python
Classifier: Programming Language :: Python :: 2.7
Classifier: Programming Language :: Python :: 3.5
Classifier: Programming Language :: Python :: 3.6
Classifier: License :: OSI Approved :: MIT License
Classifier: Topic :: Scientific/Engineering
Classifier: Topic :: Software Development
Classifier: Operating System :: POSIX :: Linux
Classifier: Intended Audience :: Science/Research
